pelican/plugins/pelican_jupyter_reader/__init__.py
pelican/plugins/pelican_jupyter_reader/pelican_jupyter_reader.py
pelican/plugins/pelican_jupyter_reader/test_pelican_jupyter_reader.py
pelican_jupyter_reader-0.3.1.dist-info/WHEEL
pelican_jupyter_reader-0.3.1.dist-info/METADATA
pelican_jupyter_reader-0.3.1.dist-info/RECORD
