Metadata-Version: 2.1
Name: pelican-jupyter-reader
Version: 0.3.1
Summary: Reader for ipynb files
Home-page: https://github.com/chuckpr/pelican-jupyter-reader
License: MIT
Keywords: pelican,plugin,jupyter
Author: Chuck Pepe-Ranney
Author-email: chuck.peperanney@gmail.com
Requires-Python: >=3.6,<4.0
Classifier: Development Status :: 1 - Planning
Classifier: Environment :: Console
Classifier: Framework :: Pelican
Classifier: Framework :: Pelican :: Plugins
Classifier: Intended Audience :: End Users/Desktop
Classifier: License :: OSI Approved :: MIT License
Classifier: Operating System :: OS Independent
Classifier: Programming Language :: Python
Classifier: Programming Language :: Python :: 3
Classifier: Programming Language :: Python :: 3.6
Classifier: Programming Language :: Python :: 3.7
Classifier: Programming Language :: Python :: 3.8
Classifier: Topic :: Internet :: WWW/HTTP
Classifier: Topic :: Software Development :: Libraries :: Python Modules
Provides-Extra: markdown
Requires-Dist: markdown (>=3.1.1,<4.0.0); extra == "markdown"
Requires-Dist: nbconvert (>=5.6.1,<6.0.0)
Requires-Dist: nbformat (>=4.4.0,<5.0.0)
Requires-Dist: pelican (>=4.2,<5.0)
Project-URL: Documentation, https://docs.getpelican.com/
Project-URL: Funding, https://donate.getpelican.com/
Project-URL: Repository, https://github.com/chuckpr/pelican-jupyter-reader
Project-URL: Source, https://github.com/chuckpr/pelican-jupyter-reader
Project-URL: Tracker, https://github.com/chuckpr/pelican-jupyter-reader/issues
